kmer_tools-0.1.2.dist-info/METADATA
kmer_tools-0.1.2.dist-info/WHEEL
kmer_tools-0.1.2.dist-info/license_files/LICENSE
kmertools/__init__.py
kmertools/kmertools.cpython-310-aarch64-linux-gnu.so
kmer_tools-0.1.2.dist-info/RECORD
